sadism.py
sadism-0.3.0.dist-info/LICENSE
sadism-0.3.0.dist-info/METADATA
sadism-0.3.0.dist-info/WHEEL
sadism-0.3.0.dist-info/top_level.txt
sadism-0.3.0.dist-info/RECORD
